xlsx2json/__init__.py
xlsx2json/__main__.py
xlsx2json/config.toml
xlsx2json/feed.py
xlsx2json/viewer.py
creepypirate_xlsx2json-1.0.0.dist-info/LICENSE
creepypirate_xlsx2json-1.0.0.dist-info/METADATA
creepypirate_xlsx2json-1.0.0.dist-info/WHEEL
creepypirate_xlsx2json-1.0.0.dist-info/top_level.txt
creepypirate_xlsx2json-1.0.0.dist-info/RECORD
